winix/__init__.py
winix/auth.py
winix/cmd.py
winix/driver.py
winix-0.3.0.dist-info/LICENSE
winix-0.3.0.dist-info/METADATA
winix-0.3.0.dist-info/WHEEL
winix-0.3.0.dist-info/entry_points.txt
winix-0.3.0.dist-info/top_level.txt
winix-0.3.0.dist-info/RECORD
