Metadata-Version: 2.1
Name: winix
Version: 0.3.0
Summary: Programmatically control the Winix C545
Home-page: https://github.com/hfern/winix
Author: Hunter Fernandes
Author-email: hunter@hfernandes.com
License: UNKNOWN
Platform: UNKNOWN
Classifier: Programming Language :: Python :: 3
Classifier: License :: OSI Approved :: MIT License
Classifier: Operating System :: OS Independent
Requires-Python: >=3.7
Requires-Dist: warrant
Requires-Dist: warrant-lite
Requires-Dist: requests
